dasifo/__init__.py
dasifo/data_storages/__init__.py
dasifo/data_storages/cloud_db.py
dasifo/data_storages/cloud_storages.py
dasifo/data_storages/db_connectors.py
dasifo/data_storages/nosql_db.py
dasifo/data_storages/sql_db.py
dasifo/scrapme/__init__.py
dasifo/scrapme/runner.py
dasifo-0.0.3.dist-info/LICENSE
dasifo-0.0.3.dist-info/METADATA
dasifo-0.0.3.dist-info/WHEEL
dasifo-0.0.3.dist-info/top_level.txt
dasifo-0.0.3.dist-info/RECORD
