Metadata-Version: 2.1
Name: dasifo
Version: 0.0.3
Summary: This new Library is 'DAta Science In Full Options = dasifo': ...
Home-page: https://github.com/larou2si/dasifo
Author: larou2si
Author-email: mohamed.laroussi.1@esprit.tn
License: UNKNOWN
Download-URL: https://github.com/larou2si/dasifo/archive/refs/tags/v0.0.1-alpha.tar.gz
Platform: UNKNOWN
Classifier: Programming Language :: Python :: 3
Classifier: License :: OSI Approved :: MIT License
Classifier: Operating System :: OS Independent
Requires-Python: >=3.7
License-File: LICENSE
Requires-Dist: numpy
Requires-Dist: scrapeasy
Requires-Dist: mysql-connector-python
Requires-Dist: psycopg2
Requires-Dist: postgis
Requires-Dist: requests
Requires-Dist: beautifulsoup4
